{
    "pattern_id": "AP_RJCH_0001",
    "departures": [
        {
            "ride_id": "JAL_2742",
            "trip_id": "JAL_2742",
            "time": "8:45",
            "departure_type": "outgoing"
        },
        {
            "ride_id": "JAL_2748",
            "trip_id": "JAL_2748",
            "time": "14:00",
            "departure_type": "outgoing"
        },
        {
            "ride_id": "JAL_2752",
            "trip_id": "JAL_2752",
            "time": "16:30",
            "departure_type": "outgoing"
        }
    ]
}